Metadata-Version: 1.1
Name: openlabs-nereid-s3
Version: 3.4.1.1
Summary: Amazon S3 backend for Nereid Static Files
Home-page: UNKNOWN
Author: UNKNOWN
Author-email: UNKNOWN
License: GPL-3
Platform: UNKNOWN
Classifier: Development Status :: 5 - Production/Stable
Classifier: Environment :: Plugins
Classifier: Framework :: Tryton
Classifier: Intended Audience :: Developers
Classifier: Intended Audience :: Financial and Insurance Industry
Classifier: Intended Audience :: Legal Industry
Classifier: Intended Audience :: Manufacturing
Classifier: License :: OSI Approved :: GNU General Public License (GPL)
Classifier: Natural Language :: English
Classifier: Operating System :: OS Independent
Classifier: Programming Language :: Python :: 2.7
Classifier: Topic :: Office/Business
